{
	"name": "IncomeBubble",
	"plugin-id": "Sprite",
	"sid": 750651943163196,
	"isGlobal": false,
	"instanceVariables": [
		{
			"name": "id",
			"type": "string",
			"desc": "",
			"show": true,
			"sid": 106025691294052
		},
		{
			"name": "duration",
			"type": "number",
			"desc": "",
			"show": true,
			"sid": 632730139043900
		},
		{
			"name": "currentDuration",
			"type": "number",
			"desc": "",
			"show": true,
			"sid": 241027232439030
		},
		{
			"name": "incomeValue",
			"type": "number",
			"desc": "",
			"show": true,
			"sid": 575232451264892
		},
		{
			"name": "tileIndex",
			"type": "number",
			"desc": "",
			"show": true,
			"sid": 350826418901145
		}
	],
	"behaviorTypes": [],
	"effectTypes": [],
	"animations": {
		"items": [
			{
				"frames": [
					{
						"width": 64,
						"height": 120,
						"originX": 0.5,
						"originY": 0.9333333333333333,
						"originalSource": "",
						"exportFormat": "lossless",
						"exportQuality": 0.8,
						"imageSpriteId": 5237778,
						"collisionPoly": {
							"points": [
								0.390625,
								0,
								0.609375,
								0,
								0.8125,
								0.05,
								0.90625,
								0.1,
								0.9375,
								0.125,
								0.96875,
								0.15833333333333333,
								1,
								0.20833333333333334,
								1,
								0.325,
								0.625,
								0.8833333333333333,
								0.546875,
								0.9333333333333333,
								0.40625,
								0.9166666666666666,
								0.375,
								0.8833333333333333,
								0,
								0.325,
								0,
								0.20833333333333334,
								0.03125,
								0.15833333333333333,
								0.0625,
								0.125,
								0.09375,
								0.1,
								0.1875,
								0.05
							]
						},
						"useCollisionPoly": true,
						"duration": 1
					},
					{
						"width": 64,
						"height": 120,
						"originX": 0.5,
						"originY": 0.9333333333333333,
						"originalSource": "",
						"exportFormat": "lossless",
						"exportQuality": 0.8,
						"imageSpriteId": 8986670,
						"collisionPoly": {
							"points": [
								0.390625,
								0,
								0.609375,
								0,
								0.8125,
								0.05,
								0.90625,
								0.1,
								0.9375,
								0.125,
								0.96875,
								0.15833333333333333,
								1,
								0.20833333333333334,
								1,
								0.325,
								0.625,
								0.8833333333333333,
								0.546875,
								0.9333333333333333,
								0.40625,
								0.9166666666666666,
								0.375,
								0.8833333333333333,
								0,
								0.325,
								0,
								0.20833333333333334,
								0.03125,
								0.15833333333333333,
								0.0625,
								0.125,
								0.09375,
								0.1,
								0.1875,
								0.05
							]
						},
						"useCollisionPoly": true,
						"duration": 1
					},
					{
						"width": 64,
						"height": 120,
						"originX": 0.5,
						"originY": 0.9333333333333333,
						"originalSource": "",
						"exportFormat": "lossless",
						"exportQuality": 0.8,
						"imageSpriteId": 9497887,
						"collisionPoly": {
							"points": [
								0.390625,
								0,
								0.609375,
								0,
								0.8125,
								0.05,
								0.90625,
								0.1,
								0.9375,
								0.125,
								0.96875,
								0.15833333333333333,
								1,
								0.20833333333333334,
								1,
								0.325,
								0.625,
								0.8833333333333333,
								0.546875,
								0.9333333333333333,
								0.40625,
								0.9166666666666666,
								0.375,
								0.8833333333333333,
								0,
								0.325,
								0,
								0.20833333333333334,
								0.03125,
								0.15833333333333333,
								0.0625,
								0.125,
								0.09375,
								0.1,
								0.1875,
								0.05
							]
						},
						"useCollisionPoly": true,
						"duration": 1
					},
					{
						"width": 64,
						"height": 120,
						"originX": 0.5,
						"originY": 0.9333333333333333,
						"originalSource": "",
						"exportFormat": "lossless",
						"exportQuality": 0.8,
						"imageSpriteId": 8367610,
						"collisionPoly": {
							"points": [
								0.390625,
								0,
								0.609375,
								0,
								0.703125,
								0.020833333333333332,
								0.765625,
								0.041666666666666664,
								0.8125,
								0.0625,
								0.90625,
								0.125,
								0.9375,
								0.15625,
								0.96875,
								0.19791666666666666,
								1,
								0.2604166666666667,
								1,
								0.4270833333333333,
								0.96875,
								0.5104166666666666,
								0.9375,
								0.5625,
								0.484375,
								1,
								0.0625,
								0.5625,
								0.03125,
								0.5104166666666666,
								0,
								0.4270833333333333,
								0,
								0.2604166666666667,
								0.03125,
								0.19791666666666666,
								0.0625,
								0.15625,
								0.09375,
								0.125,
								0.1875,
								0.0625,
								0.234375,
								0.041666666666666664,
								0.296875,
								0.020833333333333332
							]
						},
						"useCollisionPoly": true,
						"duration": 1
					},
					{
						"width": 64,
						"height": 120,
						"originX": 0.5,
						"originY": 0.9333333333333333,
						"originalSource": "",
						"exportFormat": "lossless",
						"exportQuality": 0.8,
						"imageSpriteId": 993961,
						"collisionPoly": {
							"points": [
								0.390625,
								0,
								0.609375,
								0,
								0.8125,
								0.05,
								0.90625,
								0.1,
								0.9375,
								0.125,
								0.96875,
								0.15833333333333333,
								1,
								0.20833333333333334,
								1,
								0.325,
								0.625,
								0.8833333333333333,
								0.546875,
								0.9333333333333333,
								0.40625,
								0.9166666666666666,
								0.375,
								0.8833333333333333,
								0,
								0.325,
								0,
								0.20833333333333334,
								0.03125,
								0.15833333333333333,
								0.0625,
								0.125,
								0.09375,
								0.1,
								0.1875,
								0.05
							]
						},
						"useCollisionPoly": true,
						"duration": 1
					},
					{
						"width": 64,
						"height": 120,
						"originX": 0.5,
						"originY": 0.9333333333333333,
						"originalSource": "",
						"exportFormat": "lossless",
						"exportQuality": 0.8,
						"imageSpriteId": 4599942,
						"collisionPoly": {
							"points": [
								0.390625,
								0,
								0.609375,
								0,
								0.8125,
								0.05,
								0.90625,
								0.1,
								0.9375,
								0.125,
								0.96875,
								0.15833333333333333,
								1,
								0.20833333333333334,
								1,
								0.325,
								0.625,
								0.8833333333333333,
								0.546875,
								0.9333333333333333,
								0.40625,
								0.9166666666666666,
								0.375,
								0.8833333333333333,
								0,
								0.325,
								0,
								0.20833333333333334,
								0.03125,
								0.15833333333333333,
								0.0625,
								0.125,
								0.09375,
								0.1,
								0.1875,
								0.05
							]
						},
						"useCollisionPoly": true,
						"duration": 1
					}
				],
				"sid": 987453281414430,
				"name": "Animation 1",
				"isLooping": false,
				"isPingPong": false,
				"repeatCount": 1,
				"repeatTo": 0,
				"speed": 0
			}
		],
		"subfolders": []
	}
}